Metadata-Version: 2.1
Name: adguard
Version: 0.0.1
Summary: UNKNOWN
Home-page: https://github.com/ludeeus/adguard
Author: Joakim Sorensen
Author-email: ludeeus@gmail.com
License: UNKNOWN
Platform: UNKNOWN
Classifier: Programming Language :: Python :: 3
Classifier: License :: OSI Approved :: MIT License
Classifier: Operating System :: OS Independent
